miniwob/__init__.py
miniwob/action.py
miniwob/constants.py
miniwob/dom.py
miniwob/environment.py
miniwob/fields.py
miniwob/http_server.py
miniwob/observation.py
miniwob/registration.py
miniwob/reward.py
miniwob/screenshot.py
miniwob/selenium_actions.py
miniwob/selenium_instance.py
miniwob/spaces.py
miniwob/envs/__init__.py
miniwob/envs/flightwob_envs.py
miniwob/envs/miniwob_envs.py
miniwob/html/common/shapes.js
miniwob/html/common/ui_utils.js
miniwob/html/common/special/book-flight/domestic.js
miniwob/html/common/special/checkbox-numbers/ch_0.png
miniwob/html/common/special/checkbox-numbers/ch_1.png
miniwob/html/common/special/checkbox-numbers/ch_2.png
miniwob/html/common/special/checkbox-numbers/ch_3.png
miniwob/html/common/special/checkbox-numbers/ch_4.png
miniwob/html/common/special/checkbox-numbers/ch_5.png
miniwob/html/common/special/checkbox-numbers/ch_6.png
miniwob/html/common/special/checkbox-numbers/ch_7.png
miniwob/html/common/special/checkbox-numbers/ch_8.png
miniwob/html/common/special/checkbox-numbers/ch_9.png
miniwob/html/common/special/click-pie/raphael.icons.min.js
miniwob/html/common/special/click-pie/raphael.min.js
miniwob/html/common/special/click-pie/wheelnav.min.js
miniwob/html/common/special/drag-cube/blank.png
miniwob/html/common/special/drag-cube/cube.css
miniwob/html/common/special/drag-cube/cube.js
miniwob/html/common/special/dropdown/jquery.selectric.js
miniwob/html/common/special/dropdown/selectric.css
miniwob/html/common/special/email-inbox/delete.png
miniwob/html/common/special/email-inbox/email-inbox.css
miniwob/html/common/special/email-inbox/forward.png
miniwob/html/common/special/email-inbox/left-arrow-white.png
miniwob/html/common/special/email-inbox/left-arrow.png
miniwob/html/common/special/email-inbox/reply.png
miniwob/html/common/special/email-inbox/search.png
miniwob/html/common/special/email-inbox/send.png
miniwob/html/common/special/email-inbox/star-clicked.png
miniwob/html/common/special/email-inbox/star.png
miniwob-1.0.dist-info/LICENSE
miniwob-1.0.dist-info/METADATA
miniwob-1.0.dist-info/WHEEL
miniwob-1.0.dist-info/entry_points.txt
miniwob-1.0.dist-info/top_level.txt
miniwob-1.0.dist-info/RECORD
