Metadata-Version: 2.1
Name: miniwob
Version: 1.0
Summary: A web interaction benchmark for reinforcement learning.
Author-email: Farama Foundation <contact@farama.org>
License: MIT License
Project-URL: Homepage, https://farama.org
Project-URL: Repository, https://github.com/Farama-Foundation/miniwob-plusplus
Project-URL: Documentation, https://miniwob.farama.org
Project-URL: Bug Report, https://github.com/Farama-Foundation/miniwob-plusplus/issues
Keywords: Reinforcement Learning,game,RL,AI,gymnasium
Classifier: Development Status :: 4 - Beta
Classifier: License :: OSI Approved :: MIT License
Classifier: Programming Language :: Python :: 3
Classifier: Programming Language :: Python :: 3.8
Classifier: Programming Language :: Python :: 3.9
Classifier: Programming Language :: Python :: 3.10
Classifier: Programming Language :: Python :: 3.11
Classifier: Intended Audience :: Science/Research
Classifier: Topic :: Scientific/Engineering :: Artificial Intelligence
Requires-Python: >=3.8
License-File: LICENSE
Requires-Dist: Gymnasium ==0.29.0
Requires-Dist: Pillow >=9.0.0
Requires-Dist: selenium >=4.5.0
Requires-Dist: numpy >=1.18.0
Requires-Dist: farama-notifications >=0.0.1
Provides-Extra: testing
Requires-Dist: pytest >=7.0.0 ; extra == 'testing'
Requires-Dist: pytest-timeout >=2.1.0 ; extra == 'testing'
